nimbleclient/__init__.py
nimbleclient/exceptions.py
nimbleclient/query.py
nimbleclient/resource.py
nimbleclient/v1/__init__.py
nimbleclient/v1/client.py
nimbleclient/v1/query_fields.py
nimbleclient/v1/restclient.py
nimbleclient/v1/api/__init__.py
nimbleclient/v1/api/access_control_records.py
nimbleclient/v1/api/active_directory_memberships.py
nimbleclient/v1/api/alarms.py
nimbleclient/v1/api/application_categories.py
nimbleclient/v1/api/application_servers.py
nimbleclient/v1/api/arrays.py
nimbleclient/v1/api/audit_log.py
nimbleclient/v1/api/chap_users.py
nimbleclient/v1/api/controllers.py
nimbleclient/v1/api/disks.py
nimbleclient/v1/api/events.py
nimbleclient/v1/api/fibre_channel_configs.py
nimbleclient/v1/api/fibre_channel_initiator_aliases.py
nimbleclient/v1/api/fibre_channel_interfaces.py
nimbleclient/v1/api/fibre_channel_ports.py
nimbleclient/v1/api/fibre_channel_sessions.py
nimbleclient/v1/api/folders.py
nimbleclient/v1/api/groups.py
nimbleclient/v1/api/initiator_groups.py
nimbleclient/v1/api/initiators.py
nimbleclient/v1/api/jobs.py
nimbleclient/v1/api/key_managers.py
nimbleclient/v1/api/ldap_domains.py
nimbleclient/v1/api/master_key.py
nimbleclient/v1/api/network_configs.py
nimbleclient/v1/api/network_interfaces.py
nimbleclient/v1/api/performance_policies.py
nimbleclient/v1/api/pools.py
nimbleclient/v1/api/protection_schedules.py
nimbleclient/v1/api/protection_templates.py
nimbleclient/v1/api/protocol_endpoints.py
nimbleclient/v1/api/replication_partners.py
nimbleclient/v1/api/shelves.py
nimbleclient/v1/api/snapshot_collections.py
nimbleclient/v1/api/snapshots.py
nimbleclient/v1/api/software_versions.py
nimbleclient/v1/api/space_domains.py
nimbleclient/v1/api/subnets.py
nimbleclient/v1/api/subscribers.py
nimbleclient/v1/api/subscriptions.py
nimbleclient/v1/api/tokens.py
nimbleclient/v1/api/user_groups.py
nimbleclient/v1/api/user_policies.py
nimbleclient/v1/api/users.py
nimbleclient/v1/api/versions.py
nimbleclient/v1/api/volume_collections.py
nimble_sdk-1.2.1.dist-info/LICENSE
nimble_sdk-1.2.1.dist-info/METADATA
nimble_sdk-1.2.1.dist-info/WHEEL
nimble_sdk-1.2.1.dist-info/top_level.txt
nimble_sdk-1.2.1.dist-info/RECORD
