Metadata-Version: 2.1
Name: nimble-sdk
Version: 1.2.1
Summary: The HPE Nimble Storage SDK for Python (client library) is a utility that can be leveraged to manage HPE Nimble Storage arrays.
Home-page: https://github.com/hpe-storage/nimble-python-sdk
Author: HPE Nimble Storage DCS
Author-email: nimble-dcs-storage-automation-eng@hpe.com
Maintainer: Suneethkumar Byadarahalli, Alok Ranjan, George Costea
License: Apache License, Version 2.0
Project-URL: Documentation, https://hpe-storage.github.io/nimble-python-sdk
Project-URL: Source, https://github.com/hpe-storage/nimble-python-sdk
Project-URL: Tracker, https://github.com/hpe-storage/nimble-python-sdk/issues
Project-URL: Community, https://hpedev.io
Keywords: HPE Nimble Storage REST API SDK
Platform: UNKNOWN
Classifier: Development Status :: 5 - Production/Stable
Classifier: Environment :: Console
Classifier: Intended Audience :: Developers
Classifier: Intended Audience :: Information Technology
Classifier: Intended Audience :: Science/Research
Classifier: Intended Audience :: System Administrators
Classifier: License :: OSI Approved :: Apache Software License
Classifier: Natural Language :: English
Classifier: Operating System :: OS Independent
Classifier: Programming Language :: Python :: 3.6
Classifier: Topic :: Internet :: WWW/HTTP
Classifier: Topic :: Software Development :: Libraries
Classifier: Topic :: Utilities
Requires-Python: >=3.6
Requires-Dist: requests
